cythonwheel/__init__.py
cythonwheel/package/__init__.py
cythonwheel/package/holder.py
cythonwheel/package/tests/__init__.py
cythonwheel/package/tests/properties_test.py
cythonwheel-0.1.0.dist-info/LICENSE
cythonwheel-0.1.0.dist-info/METADATA
cythonwheel-0.1.0.dist-info/WHEEL
cythonwheel-0.1.0.dist-info/RECORD
